phenom/__init__.py
phenom/api/__init__.py
phenom/api/aisourcing/__init__.py
phenom/api/aisourcing/ai_matching_api.py
phenom/api/aisourcing/models/__init__.py
phenom/api/aisourcing/models/error_response.py
phenom/api/aisourcing/models/fit_score_request.py
phenom/api/aisourcing/models/fitscore_bad_request.py
phenom/api/aisourcing/models/fitscore_response.py
phenom/api/aisourcing/models/fitscore_response_result.py
phenom/api/aisourcing/models/fitscore_response_skill_gap.py
phenom/api/aisourcing/models/preferred_locations.py
phenom/api/aisourcing/models/preferred_locations_latlong.py
phenom/api/aisourcing/models/skill_matching_bad_request.py
phenom/api/aisourcing/models/skill_matching_error_response.py
phenom/api/aisourcing/models/skill_matching_response.py
phenom/api/aisourcing/models/user_profile_fit_score.py
phenom/api/applicants/__init__.py
phenom/api/applicants/activity_api.py
phenom/api/applicants/applicants_api.py
phenom/api/applicants/hiring_status_api.py
phenom/api/applicants/leads_api.py
phenom/api/applicants/models/__init__.py
phenom/api/applicants/models/additional_fields.py
phenom/api/applicants/models/additional_fields_data.py
phenom/api/applicants/models/additional_fields_update_request.py
phenom/api/applicants/models/additional_fields_update_request_job_specific_additional_fields.py
phenom/api/applicants/models/additional_fields_update_response.py
phenom/api/applicants/models/applicants.py
phenom/api/applicants/models/applicants_data.py
phenom/api/applicants/models/applicants_data_candidates.py
phenom/api/applicants/models/applicants_data_contacts.py
phenom/api/applicants/models/applicants_pagination.py
phenom/api/applicants/models/applications.py
phenom/api/applicants/models/assign_candidates_to_job.py
phenom/api/applicants/models/bad_request.py
phenom/api/applicants/models/error.py
phenom/api/applicants/models/hiring_status.py
phenom/api/applicants/models/hiring_status_activities.py
phenom/api/applicants/models/hiring_status_activities_data.py
phenomApis-0.0.68.dist-info/LICENSE
phenomApis-0.0.68.dist-info/METADATA
phenomApis-0.0.68.dist-info/WHEEL
phenomApis-0.0.68.dist-info/top_level.txt
phenomApis-0.0.68.dist-info/RECORD
