Metadata-Version: 2.1
Name: phenomApis
Version: 0.0.68
Summary: Phenom Public Apis SDK for Python
Home-page: UNKNOWN
Author: phenom
Author-email: 8297991468h@gmail.com
License: UNKNOWN
Keywords: resumeparser,exsearch
Platform: UNKNOWN
Classifier: Development Status :: 1 - Planning
Classifier: Intended Audience :: Developers
Classifier: Programming Language :: Python :: 3
Classifier: Operating System :: Unix
Classifier: Operating System :: MacOS :: MacOS X
Classifier: Operating System :: Microsoft :: Windows
Requires-Dist: PyJWT (==2.4.0)
Requires-Dist: certifi (==2024.2.2)
Requires-Dist: urllib3 (==1.26.18)
Requires-Dist: six (==1.16.0)
